nton/__init__.py
nton/__main__.py
nton/constants.py
nton/helpers.py
nton/main.py
nton/nstool.py
nton/title_ids.py
nton/assets/control.nacp.xml
nton/assets/game_title_ids.json
nton/assets/exefs/main
nton/assets/exefs/main.npdm
nton/assets/logo/NintendoLogo.png
nton/assets/logo/StartupMovie.gif
nton/bin/hacbrewpack.exe
nton/bin/hacbrewpack.license
nton/bin/hptnacp-hacpack.license
nton/bin/hptnacp.exe
nton/bin/nstool.exe
nton/bin/nstool.license
nton/gui/__init__.py
nton/gui/logger.py
nton/gui/main.py
nton/gui/main.ui
nton/gui/widgets.py
nton-3.0.0.dist-info/METADATA
nton-3.0.0.dist-info/WHEEL
nton-3.0.0.dist-info/entry_points.txt
nton-3.0.0.dist-info/licenses/LICENSE
nton-3.0.0.dist-info/RECORD
