Metadata-Version: 2.4
Name: nton
Version: 3.0.0
Summary: Nintendo Switch NRO to NSP Forwarder.
Project-URL: Repository, https://github.com/rlaphoenix/nton
Project-URL: Issues, https://github.com/rlaphoenix/nton/issues
Project-URL: Discussions, https://github.com/rlaphoenix/nton/discussions
Project-URL: Changelog, https://github.com/rlaphoenix/nton/blob/master/CHANGELOG.md
Author-email: rlaphoenix@pm.me
License-Expression: GPL-3.0-only
License-File: LICENSE
Keywords: forwarder,homebrew,nintendo,switch
Classifier: Development Status :: 5 - Production/Stable
Classifier: Environment :: X11 Applications :: Qt
Classifier: Intended Audience :: End Users/Desktop
Classifier: Natural Language :: English
Classifier: Operating System :: Microsoft :: Windows
Classifier: Operating System :: Microsoft :: Windows :: Windows 7
Classifier: Operating System :: Microsoft :: Windows :: Windows 8
Classifier: Operating System :: Microsoft :: Windows :: Windows 8.1
Classifier: Operating System :: Microsoft :: Windows :: Windows 10
Classifier: Operating System :: Microsoft :: Windows :: Windows 11
Classifier: Topic :: Games/Entertainment
Classifier: Topic :: Utilities
Requires-Python: >=3.9
Requires-Dist: beautifulsoup4~=4.14.3
Requires-Dist: click~=8.1.8
Requires-Dist: coloredlogs~=15.0.1
Requires-Dist: jsonpickle~=4.1.1
Requires-Dist: lxml~=6.0.2
Requires-Dist: pillow~=11.3.0
Requires-Dist: requests~=2.32.5
Provides-Extra: gui
Requires-Dist: pyside6-essentials~=6.10.1; extra == 'gui'
